leodb/__init__.py
leodb/dependencies.py
leodb/core/__init__.py
leodb/core/config.py
leodb/core/connection_manager.py
leodb/core/engine.py
leodb/encryption/__init__.py
leodb/encryption/manager.py
leodb/encryption/service.py
leodb/migrations/env.py
leodb/migrations/versions/5ddbaa686ea6_create_general_schema_tables.py
leodb/models/__init__.py
leodb/models/account_base.py
leodb/models/base.py
leodb/models/account/conversation.py
leodb/models/account/conversation_context.py
leodb/models/account/data_source.py
leodb/models/account/data_source_acct.py
leodb/models/account/data_source_record.py
leodb/models/account/data_source_scheduled_task.py
leodb/models/account/data_source_user.py
leodb/models/account/message.py
leodb/models/account/project.py
leodb/models/account/project_output.py
leodb/models/account/project_step.py
leodb/models/account/project_step_data_source_association.py
leodb/models/account/project_step_tool_association.py
leodb/models/account/record.py
leodb/models/account/scheduled_task.py
leodb/models/account/scheduled_task_tool_association.py
leodb/models/account/scratchpad.py
leodb/models/account/tool_use_spec.py
leodb/models/general/account.py
leodb/models/general/account_data_connection.py
leodb/models/general/invoice.py
leodb/models/general/package.py
leodb/models/general/payment_method.py
leodb/models/general/user.py
leodb/models/general/user_invitation.py
leodb/models/general/user_preferences.py
leodb/models/general/user_session.py
leodb/models/general/user_theme_indicator.py
leodb/models/general/user_themes.py
leodb/repositories/__init__.py
leodb/repositories/account_repository.py
leodb/repositories/base_repository.py
leodb/repositories/conversation_repository.py
leodb/repositories/datasource_repository.py
leodb/repositories/invoice_repository.py
leodb/repositories/message_repository.py
leodb/repositories/package_repository.py
leodb/repositories/payment_method_repository.py
leodb/repositories/project_output_repository.py
leodbservice-0.2.21.dist-info/METADATA
leodbservice-0.2.21.dist-info/WHEEL
leodbservice-0.2.21.dist-info/top_level.txt
leodbservice-0.2.21.dist-info/RECORD
