Metadata-Version: 2.4
Name: LeoDBService
Version: 0.2.21
Summary: Librairie de service DB de l'Agent IA Leo
Project-URL: Homepage, https://github.com/StephaneBrousseauEvolv/LeoDBService
Project-URL: Repository, https://github.com/StephaneBrousseauEvolv/LeoDBService
Requires-Python: >=3.8
Requires-Dist: sqlalchemy[asyncio]
Requires-Dist: psycopg[binary]
Requires-Dist: pydantic<3.0,>=2.0
Requires-Dist: alembic
Requires-Dist: python-dotenv
Requires-Dist: azure-identity
Requires-Dist: azure-keyvault-secrets
